[
  {
    "title": "27 inch curved Samsung Monitor",
    "description": "a couple years old, works very well though",
    "room": "Office",
    "category": "Electronics",
    "status": "available",
    "image": "images/samsung monitor.jpg"
  },
  {
    "title": "Monitor arm / mount",
    "description": "black, single monitor arm, a bit scuffed from the years",
    "room": "Office",
    "category": "Accessories",
    "status": "available"
  },
  {
    "title": "Dual monitor arm / mount",
    "description": "pretty new, supports two monitors in different orientations",
    "room": "Office",
    "category": "Accessories",
    "status": "available",
    "image": "images/dual monitor arm.jpg"
  },
  {
    "title": "2020 MacBook Air",
    "description": "weakest/cheapest model from the time, needs a factory reset I reckon",
    "room": "Office",
    "category": "Electronics",
    "status": "available",
    "image": "images/macbook.jpg"
  },
  {
    "title": "A bunch of candles",
    "description": "yeah just random candles",
    "room": "Living room",
    "category": "Decor",
    "status": "available",
    "image": "images/candles.jpg"
  },
  {
    "title": "2x IKEA drawers",
    "description": "",
    "room": "Living room",
    "category": "Furniture",
    "status": "available"
  },
  {
    "title": "1x large IKEA drawer",
    "description": "",
    "room": "Living room",
    "category": "Furniture",
    "status": "available"
  },
  {
    "title": "PS4 w/ 3 controllers",
    "description": "some controllers a little scuffed but most of it works just fine",
    "room": "Living room",
    "category": "Electronics",
    "status": "available"
  },
  {
    "title": "Books",
    "description": "A selection of books",
    "room": "Living room",
    "category": "Books",
    "status": "available"
  },
  {
    "title": "Samsung 2024 QN85D Neo QLED 4k HDR Smart TV",
    "description": "55 inch model, works perfectly. With wall mount, two remotes, cables, stand. Awesome TV.",
    "room": "Living room",
    "category": "Electronics",
    "status": "available"
  },
  {
    "title": "Farmhouse dining table",
    "description": "",
    "room": "Dining room",
    "category": "Furniture",
    "status": "available"
  },
  {
    "title": "Bar cart",
    "description": "One of those random, cheap IKEA or Amazon bar carts",
    "room": "Dining room",
    "category": "Furniture",
    "status": "available"
  },
  {
    "title": "Workout bench",
    "description": "foldable workout bench, multiple angles",
    "room": "Misc",
    "category": "Fitness",
    "status": "available",
    "image": "images/workout bench.jpg"
  },
  {
    "title": "Some weights",
    "description": "ngl, they're kinda shitty",
    "room": "Misc",
    "category": "Fitness",
    "status": "available",
    "image": "images/weights.jpg"
  },
  {
    "title": "Yoga mat",
    "description": "black yoga mat",
    "room": "Misc",
    "category": "Fitness",
    "status": "available"
  },
  {
    "title": "Yoga rollers (small & large)",
    "description": "Small and large yoga roller things.",
    "room": "Misc",
    "category": "Fitness",
    "status": "available"
  },
  {
    "title": "Coat hangers / plant stands",
    "description": "",
    "room": "Misc",
    "category": "Misc",
    "status": "available"
  },
  {
    "title": "Peace lily in white pot",
    "description": "not loving life currently, but with some care could thrive again",
    "room": "Plants",
    "category": "Plants",
    "status": "available",
    "image": "images/peace lily.jpg"
  },
  {
    "title": "Wild banana (large)",
    "description": "probably needs repotting",
    "room": "Plants",
    "category": "Plants",
    "status": "available",
    "image": "images/banana.jpg"
  },
  {
    "title": "String of hearts (tiny)",
    "description": "cute little pot, not sure what this is supposed to look like tbh",
    "room": "Plants",
    "category": "Plants",
    "status": "available"
  },
  {
    "title": "Dwarf umbrella tree",
    "description": "in a glass pot, roots exposed",
    "room": "Plants",
    "category": "Plants",
    "status": "available",
    "image": "images/umbrella tree.jpg"
  },
  {
    "title": "Poinsettia",
    "description": "turns red in fall/winter season, called Christmas flower sometimes",
    "room": "Plants",
    "category": "Plants",
    "status": "available",
    "image": "images/poinsettia.jpg"
  },
  {
    "title": "Devil's ivy in beautiful pot",
    "description": "what can I say, it's a devil's ivy and it's sexy af",
    "room": "Plants",
    "category": "Plants",
    "status": "available",
    "image": "images/devils ivy.jpg"
  },
  {
    "title": "Large monstera in large pot",
    "description": "big and bulky, fat girl",
    "room": "Plants",
    "category": "Plants",
    "status": "available",
    "image": "images/large monstera large pot.jpg"
  },
  {
    "title": "Large monstera in small pot (needs repotting)",
    "description": "Needs repotting, in rough shape",
    "room": "Plants",
    "category": "Plants",
    "status": "available"
  },
  {
    "title": "Small monstera in medium pot",
    "description": "my OG monstera, could do with another pot and nice soil",
    "room": "Plants",
    "category": "Plants",
    "status": "available",
    "image": "images/small monstera.jpg"
  },
  {
    "title": "Parlour palm",
    "description": "it's a palm",
    "room": "Plants",
    "category": "Plants",
    "status": "available",
    "image": "images/parlour palm.jpg"
  },
  {
    "title": "Parlour palm 2",
    "description": "it's another palm",
    "room": "Plants",
    "category": "Plants",
    "status": "available",
    "image": "images/parlour palm 2.jpg"
  },
  {
    "title": "BBQ",
    "description": "Cosmogrill, some rust here and there, obviously used. from amazon: https://www.amazon.co.uk/dp/B0749Q79YL?ref_=ppx_hzsearch_conn_dt_b_fed_asin_title_3&th=1",
    "room": "Garden/balcony",
    "category": "Outdoor",
    "status": "available"
  },
  {
    "title": "Garden table",
    "description": "wood, foldable garden table",
    "room": "Garden/balcony",
    "category": "Outdoor",
    "status": "available"
  },
  {
    "title": "2x garden / balcony chairs",
    "description": "2 wooden foldable chairs",
    "room": "Garden/balcony",
    "category": "Outdoor",
    "status": "available"
  },
  {
    "title": "Red Pan",
    "description": "it's a pan. is red.",
    "room": "Kitchen",
    "category": "Kitchenware",
    "status": "available",
    "image": "images/red pan.jpg"
  },
  {
    "title": "Sauce Pan with Lid",
    "description": "it's a pan. it's got a lid.",
    "room": "Kitchen",
    "category": "Kitchenware",
    "status": "available",
    "image": "images/saucepan with lid.jpg"
  },
  {
    "title": "Old Pans",
    "description": "",
    "room": "Kitchen",
    "category": "Kitchenware",
    "status": "available",
    "image": "images/old pans.jpg"
  },
  {
    "title": "Rice cooker",
    "description": "single setting rice cooker, works like a charm",
    "room": "Kitchen",
    "category": "Kitchenware",
    "status": "available",
    "image": "images/rice cooker.jpg"
  },
  {
    "title": "Crock pot",
    "description": "relatively small, works well though",
    "room": "Kitchen",
    "category": "Kitchenware",
    "status": "available",
    "image": "images/crockpot.jpg"
  },
  {
    "title": "Wine rack",
    "description": "found on the street, has holes",
    "room": "Kitchen",
    "category": "Kitchenware",
    "status": "available",
    "image": "images/wine rack.jpg"
  }
]
